vas_core/__init__.py
vas_core/api_response.py
vas_core/constants.py
vas_core/middlewares.py
vas_core/settings.example.py
vas_core/settings.py
vas_core/utils.py
vas_core/app/__init__.py
vas_core/app/admin.py
vas_core/app/apps.py
vas_core/app/signals.py
vas_core/app/tests.py
vas_core/app/views.py
vas_core/app/managers/__init__.py
vas_core/app/managers/base_redis_manager.py
vas_core/app/managers/config_manager.py
vas_core/app/migrations/0001_initial.py
vas_core/app/migrations/0002_rename_deletedviacascade_accountconfig_deleted_via_cascade_and_more.py
vas_core/app/migrations/0003_biller_requires_consent_category_requires_consent.py
vas_core/app/migrations/0004_billerform_billerformfield_billerformproduct_and_more.py
vas_core/app/migrations/0005_transaction.py
vas_core/app/migrations/0006_remove_accountingentry_fees_and_more.py
vas_core/app/migrations/0007_remove_accountingentry_settlement_account_and_more.py
vas_core/app/migrations/__init__.py
vas_core/app/models/__init__.py
vas_core/app/models/accounting_entry.py
vas_core/app/models/base.py
vas_core/app/models/biller.py
vas_core/app/models/biller_field.py
vas_core/app/models/biller_form.py
vas_core/app/models/category.py
vas_core/app/models/channel.py
vas_core/app/models/country.py
vas_core/app/models/localization.py
vas_core/app/models/provider.py
vas_core/app/models/request.py
vas_core/app/models/transaction.py
vas_core/app/models/user.py
vas_core-0.0.9.dist-info/LICENSE
vas_core-0.0.9.dist-info/METADATA
vas_core-0.0.9.dist-info/WHEEL
vas_core-0.0.9.dist-info/top_level.txt
vas_core-0.0.9.dist-info/RECORD
