Metadata-Version: 2.1
Name: vas-core
Version: 0.0.9
Summary: VAS Orchestra core package
Author: Phourxx
Author-email: <phourxx0001@gmail.com>
Keywords: python,vas
Classifier: Programming Language :: Python :: 3
Classifier: License :: OSI Approved :: MIT License
Classifier: Operating System :: OS Independent
License-File: LICENSE
Requires-Dist: django
Requires-Dist: djangorestframework
Requires-Dist: djangorestframework-simplejwt
Requires-Dist: drf-yasg
Requires-Dist: python-dotenv
Requires-Dist: django-safedelete
Requires-Dist: django-cors-headers
Requires-Dist: redis
